odoo/addons/project_task_stage_mgmt/README.rst
odoo/addons/project_task_stage_mgmt/__init__.py
odoo/addons/project_task_stage_mgmt/__manifest__.py
odoo/addons/project_task_stage_mgmt/i18n/it.po
odoo/addons/project_task_stage_mgmt/i18n/project_task_stage_mgmt.pot
odoo/addons/project_task_stage_mgmt/i18n/pt_BR.po
odoo/addons/project_task_stage_mgmt/readme/CONTRIBUTORS.md
odoo/addons/project_task_stage_mgmt/readme/DESCRIPTION.md
odoo/addons/project_task_stage_mgmt/static/description/icon.png
odoo/addons/project_task_stage_mgmt/static/description/index.html
odoo/addons/project_task_stage_mgmt/views/project.xml
odoo_addon_project_task_stage_mgmt-18.0.1.0.0.2.dist-info/METADATA
odoo_addon_project_task_stage_mgmt-18.0.1.0.0.2.dist-info/WHEEL
odoo_addon_project_task_stage_mgmt-18.0.1.0.0.2.dist-info/top_level.txt
odoo_addon_project_task_stage_mgmt-18.0.1.0.0.2.dist-info/RECORD
